odoo/addons/base_geoengine_demo/README.rst
odoo/addons/base_geoengine_demo/__init__.py
odoo/addons/base_geoengine_demo/__manifest__.py
odoo/addons/base_geoengine_demo/data/npa_geom.xml
odoo/addons/base_geoengine_demo/data/retail_machine_geom.xml
odoo/addons/base_geoengine_demo/i18n/base_geoengine_demo.pot
odoo/addons/base_geoengine_demo/i18n/es.po
odoo/addons/base_geoengine_demo/i18n/it.po
odoo/addons/base_geoengine_demo/i18n/zh_CN.po
odoo/addons/base_geoengine_demo/models/__init__.py
odoo/addons/base_geoengine_demo/models/geo_npa.py
odoo/addons/base_geoengine_demo/models/retail_machine.py
odoo/addons/base_geoengine_demo/readme/CONTRIBUTORS.md
odoo/addons/base_geoengine_demo/readme/DESCRIPTION.md
odoo/addons/base_geoengine_demo/readme/INSTALL.md
odoo/addons/base_geoengine_demo/readme/USAGE.md
odoo/addons/base_geoengine_demo/security/ir.model.access.csv
odoo/addons/base_geoengine_demo/static/description/icon.png
odoo/addons/base_geoengine_demo/static/description/index.html
odoo/addons/base_geoengine_demo/static/img/map.png
odoo/addons/base_geoengine_demo/views/menus.xml
odoo/addons/base_geoengine_demo/views/retail_machine.xml
odoo/addons/base_geoengine_demo/views/zip.xml
odoo_addon_base_geoengine_demo-17.0.1.0.1.dist-info/METADATA
odoo_addon_base_geoengine_demo-17.0.1.0.1.dist-info/WHEEL
odoo_addon_base_geoengine_demo-17.0.1.0.1.dist-info/top_level.txt
odoo_addon_base_geoengine_demo-17.0.1.0.1.dist-info/RECORD
