Metadata-Version: 2.1
Name: odoo-addon-base_geoengine_demo
Version: 17.0.1.0.1
Requires-Python: >=3.10
Requires-Dist: geojson
Requires-Dist: odoo-addon-base_geoengine>=17.0dev,<17.1dev
Requires-Dist: odoo>=17.0a,<17.1dev
Summary: Geo spatial support Demo
Home-page: https://github.com/OCA/geospatial
License: AGPL-3
Author: Camptocamp,Odoo Community Association (OCA)
Author-email: support@odoo-community.org
Classifier: Programming Language :: Python
Classifier: Framework :: Odoo
Classifier: Framework :: Odoo :: 17.0
Classifier: License :: OSI Approved :: GNU Affero General Public License v3
